mkdocs_simple_plugin/.pages
mkdocs_simple_plugin/README.md
mkdocs_simple_plugin/__init__.py
mkdocs_simple_plugin/generator.py
mkdocs_simple_plugin/plugin.py
mkdocs_simple_plugin/semiliterate.py
mkdocs_simple_plugin/simple.py
mkdocs_simple_plugin-3.2.4.dist-info/METADATA
mkdocs_simple_plugin-3.2.4.dist-info/WHEEL
mkdocs_simple_plugin-3.2.4.dist-info/entry_points.txt
mkdocs_simple_plugin-3.2.4.dist-info/licenses/LICENSE
mkdocs_simple_plugin-3.2.4.dist-info/RECORD
