Metadata-Version: 2.4
Name: mkdocs-simple-plugin
Version: 3.2.4
Summary: Plugin for adding simple wiki site creation from markdown files interspersed within your code with MkDocs.
Project-URL: Documentation, http://www.althack.dev/mkdocs-simple-plugin
Project-URL: Homepage, http://www.althack.dev/mkdocs-simple-plugin
Project-URL: Issues, https://github.com/athackst/mkdocs-simple-plugin/issues
Project-URL: Source Code, https://github.com/athackst/mkdocs-simple-plugin
Author-email: Allison Thackston <allison@allisonthackston.com>
License-Expression: Apache-2.0
License-File: LICENSE
Keywords: mkdocs,readme,wiki
Classifier: Development Status :: 4 - Beta
Classifier: Intended Audience :: Developers
Classifier: Intended Audience :: Information Technology
Classifier: Programming Language :: Python
Classifier: Programming Language :: Python :: 3 :: Only
Classifier: Programming Language :: Python :: 3.8
Classifier: Programming Language :: Python :: 3.9
Classifier: Programming Language :: Python :: 3.10
Classifier: Programming Language :: Python :: 3.11
Requires-Python: >=3
Requires-Dist: click>=7.1
Requires-Dist: markupsafe>=2.1.1
Requires-Dist: mkdocs>=1.6.0
Requires-Dist: pyyaml>=6.0
